skill_mac_application_launcher/__init__.py
skill_mac_application_launcher/macos_controller.py
skill_mac_application_launcher/py.typed
skill_mac_application_launcher/version.py
skill_mac_application_launcher/locale/ca-es/already_running.dialog
skill_mac_application_launcher/locale/ca-es/close.intent
skill_mac_application_launcher/locale/ca-es/confirm_launch.dialog
skill_mac_application_launcher/locale/ca-es/confirm_switch.dialog
skill_mac_application_launcher/locale/ca-es/launch.intent
skill_mac_application_launcher/locale/ca-es/skill.json
skill_mac_application_launcher/locale/da/already_running.dialog
skill_mac_application_launcher/locale/da/close.intent
skill_mac_application_launcher/locale/da/confirm_launch.dialog
skill_mac_application_launcher/locale/da/confirm_switch.dialog
skill_mac_application_launcher/locale/da/launch.intent
skill_mac_application_launcher/locale/da/skill.json
skill_mac_application_launcher/locale/de-de/already_running.dialog
skill_mac_application_launcher/locale/de-de/close.intent
skill_mac_application_launcher/locale/de-de/confirm_launch.dialog
skill_mac_application_launcher/locale/de-de/confirm_switch.dialog
skill_mac_application_launcher/locale/de-de/launch.intent
skill_mac_application_launcher/locale/de-de/skill.json
skill_mac_application_launcher/locale/en-us/already_running.dialog
skill_mac_application_launcher/locale/en-us/close.intent
skill_mac_application_launcher/locale/en-us/confirm_launch.dialog
skill_mac_application_launcher/locale/en-us/confirm_switch.dialog
skill_mac_application_launcher/locale/en-us/launch.intent
skill_mac_application_launcher/locale/en-us/skill.json
skill_mac_application_launcher/locale/eu/launch.intent
skill_mac_application_launcher/locale/gl-es/already_running.dialog
skill_mac_application_launcher/locale/gl-es/close.intent
skill_mac_application_launcher/locale/gl-es/confirm_launch.dialog
skill_mac_application_launcher/locale/gl-es/confirm_switch.dialog
skill_mac_application_launcher-0.1.0.dist-info/METADATA
skill_mac_application_launcher-0.1.0.dist-info/WHEEL
skill_mac_application_launcher-0.1.0.dist-info/entry_points.txt
skill_mac_application_launcher-0.1.0.dist-info/licenses/LICENSE
skill_mac_application_launcher-0.1.0.dist-info/RECORD
