Metadata-Version: 2.4
Name: skill-mac-application-launcher
Version: 0.1.0
Summary: Launch Mac desktop applications by voice
Project-URL: Homepage, https://github.com/OscillateLabsLLC/skill-mac-application-launcher
Project-URL: Repository, https://github.com/OscillateLabsLLC/skill-mac-application-launcher
Project-URL: Bug Tracker, https://github.com/OscillateLabsLLC/skill-mac-application-launcher/issues
Author-email: OscillateLabsLLC <mike@oscillatelabs.net>
License-Expression: Apache-2.0
License-File: LICENSE
Keywords: application,launcher,macos,neon,ovos,plugin,skill
Classifier: Intended Audience :: Developers
Classifier: Operating System :: MacOS
Classifier: Programming Language :: Python :: 3
Classifier: Topic :: Multimedia
Classifier: Topic :: Software Development :: Libraries :: Python Modules
Requires-Python: >=3.9
Requires-Dist: ovos-bus-client>=1.3.4
Requires-Dist: ovos-plugin-manager~=0.9.0
Requires-Dist: ovos-utils>=0.8.1
Requires-Dist: ovos-workshop>=3.1.2
Requires-Dist: padacioso>=0.1.1
Requires-Dist: psutil
